{"teams":[{"idTeam":"136474","idESPN":"0","idAPIfootball":"1502","intLoved":null,"strTeam":"Burkina Faso","strTeamAlternate":"Upper Volta","strTeamShort":"BUR","intFormedYear":"1960","strSport":"Soccer","strLeague":"World Cup Qualifying CAF","idLeague":"5514","strLeague2":"African Cup of Nations","idLeague2":"4496","strLeague3":"International Friendlies","idLeague3":"4562","strLeague4":"African Cup of Nations Qualifying","idLeague4":"5520","strLeague5":"","idLeague5":null,"strLeague6":"","idLeague6":null,"strLeague7":"","idLeague7":null,"strDivision":null,"idVenue":"0","strStadium":"","strKeywords":"Les Étalons (The Stallions)","strRSS":"","strLocation":"Ouagadougou, Burkina Faso","intStadiumCapacity":"35000","strWebsite":"","strFacebook":"","strTwitter":"","strInstagram":"","strDescriptionEN":"The Burkina Faso national football team (French: Équipe nationale de football du Burkina Faso), represents Burkina Faso in men's international football and is controlled by the Burkinabé Football Federation. They were known as the Upper Volta national football team until 1984, when Upper Volta became Burkina Faso. They finished fourth in the 1998 Africa Cup of Nations, when they hosted the tournament. Their best ever finish in the tournament was the 2013 edition, reaching the final, The team represents both FIFA and Confederation of African Football (CAF).","strDescriptionDE":null,"strDescriptionFR":null,"strDescriptionCN":null,"strDescriptionIT":null,"strDescriptionJP":null,"strDescriptionRU":null,"strDescriptionES":null,"strDescriptionPT":null,"strDescriptionSE":null,"strDescriptionNL":null,"strDescriptionHU":null,"strDescriptionNO":null,"strDescriptionIL":null,"strDescriptionPL":null,"strColour1":"#009E49","strColour2":"#EF2B2D","strColour3":"#FFFFFF","strGender":"Male","strCountry":"Burkina Faso","strBadge":"https://r2.thesportsdb.com/images/media/team/badge/y38bkz1742102697.png","strLogo":"https://r2.thesportsdb.com/images/media/team/logo/76u8he1740099504.png","strFanart1":"https://r2.thesportsdb.com/images/media/team/fanart/5izymo1740099505.jpg","strFanart2":null,"strFanart3":null,"strFanart4":null,"strBanner":null,"strEquipment":null,"strYoutube":"","strLocked":"unlocked"}]}