{"teams":[{"idTeam":"136483","idESPN":"0","idAPIfootball":"1506","intLoved":null,"strTeam":"Ethiopia","strTeamAlternate":"","strTeamShort":"","intFormedYear":"1947","strSport":"Soccer","strLeague":"World Cup Qualifying CAF","idLeague":"5514","strLeague2":"African Cup of Nations Qualifying","idLeague2":"5520","strLeague3":"International Friendlies","idLeague3":"4562","strLeague4":"","idLeague4":null,"strLeague5":"","idLeague5":null,"strLeague6":"","idLeague6":null,"strLeague7":"","idLeague7":null,"strDivision":null,"idVenue":"18544","strStadium":"Addis Ababa Stadium","strKeywords":"","strRSS":"","strLocation":"Addis Ababa, Ethiopia","intStadiumCapacity":"35000","strWebsite":"","strFacebook":"","strTwitter":"","strInstagram":"","strDescriptionEN":"The Ethiopia national football team—nicknamed \"Walias,\" after the Walia ibex, represents Ethiopia in association football and is presided over by the Ethiopian Football Federation, the governing body for football in Ethiopia. The team has been representing Ethiopia in regional, continental, and international competitions since its founding in 1943. The Walias play their home games at Addis Ababa Stadium located in the capital city of Addis Ababa. They are currently ranked 150th in the world according to the FIFA World Rankings and 44th in CAF.\r\n\r\nEthiopia was one of only three teams (along with Egypt and Sudan) to participate in the inaugural Africa Cup of Nations in 1957. It won the competition in 1962, while it was also the host. However, success has been elusive since the end of the 1960s. Under a previous coach Sewnet Bishaw, the team qualified for the 2013 African Cup of Nations after a 31-year absence.","strDescriptionDE":null,"strDescriptionFR":null,"strDescriptionCN":null,"strDescriptionIT":null,"strDescriptionJP":null,"strDescriptionRU":null,"strDescriptionES":null,"strDescriptionPT":null,"strDescriptionSE":null,"strDescriptionNL":null,"strDescriptionHU":null,"strDescriptionNO":null,"strDescriptionIL":null,"strDescriptionPL":null,"strColour1":"","strColour2":"","strColour3":"","strGender":"Male","strCountry":"Ethiopia","strBadge":"https://r2.thesportsdb.com/images/media/team/badge/5byztx1728749764.png","strLogo":"https://r2.thesportsdb.com/images/media/team/logo/kfrh8w1740103516.png","strFanart1":"https://r2.thesportsdb.com/images/media/team/fanart/y4bnx71740103519.jpg","strFanart2":null,"strFanart3":null,"strFanart4":null,"strBanner":null,"strEquipment":null,"strYoutube":"","strLocked":"unlocked"}]}