{"teams":[{"idTeam":"134513","idESPN":"0","idAPIfootball":"1504","intLoved":null,"strTeam":"Ghana","strTeamAlternate":"","strTeamShort":"GHA","intFormedYear":"1950","strSport":"Soccer","strLeague":"FIFA World Cup","idLeague":"4429","strLeague2":"African Cup of Nations Qualifying","idLeague2":"5520","strLeague3":"International Friendlies","idLeague3":"4562","strLeague4":"World Cup Qualifying CAF","idLeague4":"5514","strLeague5":"","idLeague5":null,"strLeague6":"","idLeague6":null,"strLeague7":"","idLeague7":null,"strDivision":null,"idVenue":"23198","strStadium":"Accra Sports Stadium","strKeywords":"","strRSS":"","strLocation":"Ghana","intStadiumCapacity":"0","strWebsite":"","strFacebook":"","strTwitter":"","strInstagram":"","strDescriptionEN":"The Ghana national football team represents Ghana in international association football and has done so since the 1950s. The team is nicknamed the Black Stars after the Black Star of Africa in the flag of Ghana. It is administered by the Ghana Football Association, the governing body for football in Ghana and the oldest football association in Africa (founded in 1920). Prior to 1957, the team played as the Gold Coast.\r\n\r\nAlthough the team qualified for the senior FIFA World Cup for the first time in 2006, they had qualified for four Olympic Games Football Tournaments when the tournament was still a full senior national team competition; their best achievement was the third position at the 1992 Summer Olympics. The team has won the Africa Cup of Nations four times (in 1963, 1965, 1978, and 1982) and has been runner-up five times (in 1968, 1970, 1992, 2010, and 2015). After going through 2005 unbeaten, the Ghana national football team won the FIFA Best Mover of the Year Award and reached the second round of the 2006 FIFA World Cup. At the 2010 FIFA World Cup in South Africa, they became only the third African team to reach the World Cup quarter-finals, and in 2014 they competed in their third consecutive World Cup.","strDescriptionDE":null,"strDescriptionFR":null,"strDescriptionCN":null,"strDescriptionIT":null,"strDescriptionJP":null,"strDescriptionRU":null,"strDescriptionES":null,"strDescriptionPT":null,"strDescriptionSE":null,"strDescriptionNL":null,"strDescriptionHU":null,"strDescriptionNO":null,"strDescriptionIL":null,"strDescriptionPL":null,"strColour1":"#ffffff","strColour2":"#D40023","strColour3":"#FFE500","strGender":"Male","strCountry":"Ghana","strBadge":"https://r2.thesportsdb.com/images/media/team/badge/j589xw1751526124.png","strLogo":"https://r2.thesportsdb.com/images/media/team/logo/jhalsc1740105058.png","strFanart1":"https://r2.thesportsdb.com/images/media/team/fanart/bww3ep1740105057.jpg","strFanart2":"https://r2.thesportsdb.com/images/media/team/fanart/48oiqf1780490149.jpg","strFanart3":"https://r2.thesportsdb.com/images/media/team/fanart/8b5e7t1780490155.jpg","strFanart4":"https://r2.thesportsdb.com/images/media/team/fanart/48jeuz1780490160.jpg","strBanner":"https://r2.thesportsdb.com/images/media/team/banner/2kds0w1780490873.jpg","strEquipment":"https://r2.thesportsdb.com/images/media/team/equipment/9zauvk1780569222.png","strYoutube":"","strLocked":"unlocked"}]}