{"teams":[{"idTeam":"135988","idESPN":"0","idAPIfootball":"18","intLoved":null,"strTeam":"Iceland","strTeamAlternate":"Ísland, Islande, Исландия, アイスランド","strTeamShort":"ICE","intFormedYear":"1930","strSport":"Soccer","strLeague":"World Cup Qualifying UEFA","idLeague":"5518","strLeague2":"UEFA Nations League","idLeague2":"4490","strLeague3":"International Friendlies","idLeague3":"4562","strLeague4":"UEFA European Championships Qualifying","idLeague4":"5519","strLeague5":"","idLeague5":null,"strLeague6":"","idLeague6":null,"strLeague7":"","idLeague7":null,"strDivision":null,"idVenue":"17421","strStadium":"Laugardalsvöllur","strKeywords":"\tStrákarnir okkar","strRSS":"","strLocation":"Reykjavík, Iceland","intStadiumCapacity":"9800","strWebsite":"www.ksi.is","strFacebook":"","strTwitter":"","strInstagram":"","strDescriptionEN":"The Iceland national football team (Icelandic: Íslenska karlalandsliðið í knattspyrnu) represents Iceland in men's international football. The team is controlled by the Football Association of Iceland, and have been an FIFA member since 1947 and an UEFA member since 1957. The team's nickname is Strákarnir okkar meaning our boys.\r\n\r\nThe team has enjoyed success in the second half of the 2010s. In the qualifying rounds for the 2014 FIFA World Cup, Iceland reached the playoffs before losing to Croatia. Iceland reached its first major tournament, UEFA Euro 2016, after a qualification campaign which included home and away wins over the Netherlands. After advancing to the knockout stages of Euro 2016, Iceland defeated England in the Round of 16, advancing to the quarter-finals, where they lost to host nation France 5–2. They became the smallest nation by population to ever clinch a FIFA World Cup berth when they qualified for the 2018 tournament on 9 October 2017. They drew with Argentina in their opening match, but nonetheless still went out in the group stage.","strDescriptionDE":null,"strDescriptionFR":null,"strDescriptionCN":null,"strDescriptionIT":null,"strDescriptionJP":null,"strDescriptionRU":null,"strDescriptionES":null,"strDescriptionPT":null,"strDescriptionSE":null,"strDescriptionNL":null,"strDescriptionHU":null,"strDescriptionNO":null,"strDescriptionIL":null,"strDescriptionPL":null,"strColour1":"","strColour2":"","strColour3":"","strGender":"Male","strCountry":"Iceland","strBadge":"https://r2.thesportsdb.com/images/media/team/badge/xc6kuy1742982312.png","strLogo":"https://r2.thesportsdb.com/images/media/team/logo/197wlo1591971269.png","strFanart1":null,"strFanart2":null,"strFanart3":null,"strFanart4":null,"strBanner":null,"strEquipment":"https://r2.thesportsdb.com/images/media/team/equipment/zx6o5c1613401992.png","strYoutube":"","strLocked":"unlocked"}]}