{"teams":[{"idTeam":"140165","idESPN":"0","idAPIfootball":"1539","intLoved":null,"strTeam":"Turkmenistan","strTeamAlternate":"Түркменистан, Turkmenia, تركمانستان, Turquemenistão, Туркмения, 土库曼斯坦","strTeamShort":"TUR","intFormedYear":"1992","strSport":"Soccer","strLeague":"World Cup Qualifying AFC","idLeague":"5513","strLeague2":"International Friendlies","idLeague2":"4562","strLeague3":"AFC Asian Cup Qualifying","idLeague3":"5521","strLeague4":"CAFA Nations Cup","idLeague4":"5683","strLeague5":"","idLeague5":null,"strLeague6":"","idLeague6":null,"strLeague7":"","idLeague7":null,"strDivision":null,"idVenue":"0","strStadium":"","strKeywords":"\tEmerald","strRSS":"","strLocation":"Ashgabat, Turkmenistan","intStadiumCapacity":"26503","strWebsite":"","strFacebook":"www.facebook.com/turkmenfootball","strTwitter":"","strInstagram":"","strDescriptionEN":"The Turkmenistan national football team (Turkmen: Türkmenistanyň milli futbol ýygyndysy) represents Turkmenistan in association football and is controlled by the Football Federation of Turkmenistan, the governing body for football in Turkmenistan. Turkmenistan's home ground is Kopetdag Stadium in Ashgabat.","strDescriptionDE":null,"strDescriptionFR":null,"strDescriptionCN":null,"strDescriptionIT":null,"strDescriptionJP":null,"strDescriptionRU":null,"strDescriptionES":null,"strDescriptionPT":null,"strDescriptionSE":null,"strDescriptionNL":null,"strDescriptionHU":null,"strDescriptionNO":null,"strDescriptionIL":null,"strDescriptionPL":null,"strColour1":"","strColour2":"","strColour3":"","strGender":"Male","strCountry":"Turkmenistan","strBadge":"https://r2.thesportsdb.com/images/media/team/badge/8z5f421597942002.png","strLogo":"https://r2.thesportsdb.com/images/media/team/logo/uds13f1597942002.png","strFanart1":null,"strFanart2":null,"strFanart3":null,"strFanart4":null,"strBanner":null,"strEquipment":null,"strYoutube":"","strLocked":"unlocked"}]}